{
  "id": "e49164ce-f2c5-46e5-9217-a097cdb37037",
  "alias": "BannerPlanoDiretorWebPart",
  "componentType": "WebPart",
  "version": "0.0.1",
  "manifestVersion": 2,
  "requiresCustomScript": false,
  "supportedHosts": [
    "SharePointWebPart",
    "TeamsPersonalApp",
    "TeamsTab",
    "SharePointFullPage"
  ],
  "supportsThemeVariants": true,
  "supportsFullBleed": true,
  "preconfiguredEntries": [
    {
      "groupId": "5c03119e-3074-46fd-976b-c60198311f70",
      "group": {
        "default": "Advanced"
      },
      "title": {
        "default": "bannerPlanoDiretor"
      },
      "description": {
        "default": "bannerPlanoDiretor description"
      },
      "officeFabricIconFontName": "Page",
      "properties": {
        "description": "bannerPlanoDiretor"
      }
    }
  ],
  "loaderConfig": {
    "internalModuleBaseUrls": [
      "<!-- PATH TO CDN -->"
    ],
    "entryModuleId": "banner-plano-diretor-web-part",
    "scriptResources": {
      "banner-plano-diretor-web-part": {
        "type": "path",
        "path": "banner-plano-diretor-web-part_a81e1945223834d9d729.js"
      },
      "@microsoft/sp-property-pane": {
        "type": "component",
        "id": "f9e737b7-f0df-4597-ba8c-3060f82380db",
        "version": "1.11.0"
      },
      "AppWebPartStrings": {
        "type": "path",
        "path": "AppWebPartStrings_en-us_ab0373b2a20479e31e6fa297c55f351c.js"
      },
      "@microsoft/sp-webpart-base": {
        "type": "component",
        "id": "974a7777-0990-4136-8fa6-95d80114c2e0",
        "version": "1.11.0"
      },
      "react": {
        "type": "component",
        "id": "0d910c1c-13b9-4e1c-9aa4-b008c5e42d7d",
        "version": "16.13.1"
      },
      "react-dom": {
        "type": "component",
        "id": "aa0a46ec-1505-43cd-a44a-93f3a5aa460a",
        "version": "16.13.1"
      }
    }
  }
}